{
    "location": "Greater Toronto Area",
    "email": "yjdeng13@yahoo.com",
    "resume": "resume/YDeng_resume.html",
    "linkedin": "https://www.linkedin.com/in/yangjia-deng-9b488656/",
    "github": "https://github.com/yang530",
    "per_stmt": [
        "Hello! Welcome to my personal website. Please call me Yang. I am a recent graduate of the Interactive Media Management (IMM) program at Sheridan College.",
        "\n\n",
        "I am interested in becoming a web developer, particularly in web interactive design and front end development. Coding and interactive technologies have always been my interest. Prior to learning web development, I have 8 years of object oriented programming experience in Java, C++ and C#.",
        "\n\n\n"
    ]
}